datarack/__init__.py
datarack/datarack.py
datarack-0.2.5.dist-info/licenses/LICENSE
datarack-0.2.5.dist-info/METADATA
datarack-0.2.5.dist-info/WHEEL
datarack-0.2.5.dist-info/top_level.txt
datarack-0.2.5.dist-info/RECORD
