Metadata-Version: 2.4
Name: datarack
Version: 0.2.5
Summary: Manage data easily and efficiently
Author: TrattyGod
License: DataRack License [DataRack] Copyright (C) [2025] [TrattyGod]
Project-URL: Homepage, https://github.com/TrattyGod/DataRack-Python-Library/
Keywords: data,storage,data-management
Classifier: Development Status :: 3 - Alpha
Classifier: Intended Audience :: Developers
Classifier: Programming Language :: Python :: 3
Classifier: Programming Language :: Python :: 3.8
Classifier: Programming Language :: Python :: 3.9
Classifier: Programming Language :: Python :: 3.10
License-File: LICENSE
Dynamic: license-file
